darkchallenge/__init__.py
darkchallenge/db/__init__.py
darkchallenge/db/base.py
darkchallenge/server/__init__.py
darkchallenge/server/core.py
darkchallenge-202303141606.dist-info/METADATA
darkchallenge-202303141606.dist-info/WHEEL
darkchallenge-202303141606.dist-info/top_level.txt
darkchallenge-202303141606.dist-info/RECORD
