Metadata-Version: 2.1
Name: darkchallenge
Version: 202303141606
Summary: darkchallenge
Home-page: https://github.com/1007530194
Author: niuliangtao
Author-email: 1007530194@qq.com
Requires-Dist: sqlalchemy
Requires-Dist: darksecret
